hello/__init__.py
hello/hello.py
hellolibalec-0.0.1.dist-info/METADATA
hellolibalec-0.0.1.dist-info/WHEEL
hellolibalec-0.0.1.dist-info/top_level.txt
hellolibalec-0.0.1.dist-info/RECORD
