Metadata-Version: 2.1
Name: hellolibalec
Version: 0.0.1
Summary: A basic hello package
Home-page: UNKNOWN
Author: Alecgrater
Author-email: <alecgrater@gmail.com>
License: UNKNOWN
Keywords: python,learning,useless
Platform: UNKNOWN
Classifier: Development Status :: 1 - Planning
Classifier: Intended Audience :: Developers
Classifier: Programming Language :: Python :: 3
Classifier: Operating System :: Unix
Classifier: Operating System :: MacOS :: MacOS X
Classifier: Operating System :: Microsoft :: Windows
